{
  "timestamp": 1756323889.2572489,
  "meta": {
    "params": {
      "area": 1,
      "per_page": 50,
      "only_with_salary": false,
      "text": "python",
      "page": 10,
      "period": 1
    }
  },
  "data": {
    "items": [
      {
        "id": "124564584",
        "premium": false,
        "name": "Администратор баз данных, Kafka/Clickhouse, Ozon Банк",
        "department": {
          "id": "ozonru-2180-fintech",
          "name": "Ozon Банк"
        },
        "has_test": false,
        "response_letter_required": false,
        "area": {
          "id": "1",
          "name": "Москва",
          "url": "https://api.hh.ru/areas/1"
        },
        "salary": null,
        "salary_range": null,
        "type": {
          "id": "open",
          "name": "Открытая"
        },
        "address": null,
        "response_url": null,
        "sort_point_distance": null,
        "published_at": "2025-08-27T22:30:18+0300",
        "created_at": "2025-08-27T22:30:18+0300",
        "archived": false,
        "apply_alternate_url": "https://hh.ru/applicant/vacancy_response?vacancyId=124564584",
        "branding": {
          "type": "MAKEUP",
          "tariff": null
        },
        "show_logo_in_search": true,
        "show_contacts": false,
        "insider_interview": null,
        "url": "https://api.hh.ru/vacancies/124564584?host=hh.ru",
        "alternate_url": "https://hh.ru/vacancy/124564584",
        "relations": [],
        "employer": {
          "id": "2180",
          "name": "Ozon",
          "url": "https://api.hh.ru/employers/2180",
          "alternate_url": "https://hh.ru/employer/2180",
          "logo_urls": {
            "original": "https://img.hhcdn.ru/employer-logo-original/1069622.png",
            "90": "https://img.hhcdn.ru/employer-logo/5899117.png",
            "240": "https://img.hhcdn.ru/employer-logo/5899118.png"
          },
          "vacancies_url": "https://api.hh.ru/vacancies?employer_id=2180",
          "accredited_it_employer": true,
          "trusted": true
        },
        "snippet": {
          "requirement": "Будет плюсом: Опыт работа с Gitlab, Ansible. Знание и практические навыки SQL. Знание Bash/<highlighttext>Python</highlighttext>/Go для автоматизации рутинных задач.",
          "responsibility": "Администрирование Clickhouse/Kafka. Установка и настройка Clickhouse/Kafka. Развитие мониторинга, алертинга и резервного копирования Clickhouse/Kafka. Выполнение обращений и заявок..."
        },
        "contacts": null,
        "schedule": {
          "id": "remote",
          "name": "Удаленная работа"
        },
        "working_days": [],
        "working_time_intervals": [],
        "working_time_modes": [],
        "accept_temporary": false,
        "fly_in_fly_out_duration": [],
        "work_format": [
          {
            "id": "REMOTE",
            "name": "Удалённо"
          },
          {
            "id": "HYBRID",
            "name": "Гибрид"
          }
        ],
        "working_hours": [
          {
            "id": "HOURS_8",
            "name": "8 часов"
          }
        ],
        "work_schedule_by_days": [
          {
            "id": "FIVE_ON_TWO_OFF",
            "name": "5/2"
          }
        ],
        "night_shifts": false,
        "professional_roles": [
          {
            "id": "113",
            "name": "Системный администратор"
          }
        ],
        "accept_incomplete_resumes": false,
        "experience": {
          "id": "between3And6",
          "name": "От 3 до 6 лет"
        },
        "employment": {
          "id": "full",
          "name": "Полная занятость"
        },
        "employment_form": {
          "id": "FULL",
          "name": "Полная"
        },
        "internship": false,
        "adv_response_url": null,
        "is_adv_vacancy": false,
        "adv_context": null
      },
      {
        "id": "124557987",
        "premium": false,
        "name": "Frontend-разработчик",
        "department": null,
        "has_test": false,
        "response_letter_required": false,
        "area": {
          "id": "2053",
          "name": "Одинцово (Московская область)",
          "url": "https://api.hh.ru/areas/2053"
        },
        "salary": {
          "from": 265000,
          "to": 290000,
          "currency": "RUR",
          "gross": true
        },
        "salary_range": {
          "from": 265000,
          "to": 290000,
          "currency": "RUR",
          "gross": true,
          "mode": {
            "id": "MONTH",
            "name": "За месяц"
          },
          "frequency": null
        },
        "type": {
          "id": "open",
          "name": "Открытая"
        },
        "address": {
          "city": null,
          "street": null,
          "building": null,
          "lat": null,
          "lng": null,
          "description": null,
          "raw": null,
          "metro": {
            "station_name": "Баковка",
            "line_name": "МЦД-1",
            "station_id": "131.709",
            "line_id": "131",
            "lat": 55.682816,
            "lng": 37.315205
          },
          "metro_stations": [
            {
              "station_name": "Баковка",
              "line_name": "МЦД-1",
              "station_id": "131.709",
              "line_id": "131",
              "lat": 55.682816,
              "lng": 37.315205
            },
            {
              "station_name": "Немчиновка",
              "line_name": "МЦД-1",
              "station_id": "131.707",
              "line_id": "131",
              "lat": 55.715668,
              "lng": 37.374611
            },
            {
              "station_name": "Переделкино",
              "line_name": "МЦД-4",
              "station_id": "136.907",
              "line_id": "136",
              "lat": 55.656111,
              "lng": 37.353889
            },
            {
              "station_name": "Сетунь",
              "line_name": "МЦД-1",
              "station_id": "131.706",
              "line_id": "131",
              "lat": 55.723713,
              "lng": 37.397259
            }
          ],
          "id": "19266625"
        },
        "response_url": null,
        "sort_point_distance": null,
        "published_at": "2025-08-27T16:43:23+0300",
        "created_at": "2025-08-27T16:43:23+0300",
        "archived": false,
        "apply_alternate_url": "https://hh.ru/applicant/vacancy_response?vacancyId=124557987",
        "show_logo_in_search": null,
        "show_contacts": false,
        "insider_interview": null,
        "url": "https://api.hh.ru/vacancies/124557987?host=hh.ru",
        "alternate_url": "https://hh.ru/vacancy/124557987",
        "relations": [],
        "employer": {
          "id": "637743",
          "name": "Агентство КИТ Консалт",
          "url": "https://api.hh.ru/employers/637743",
          "alternate_url": "https://hh.ru/employer/637743",
          "logo_urls": {
            "original": "https://img.hhcdn.ru/employer-logo-original/1395338.png",
            "90": "https://img.hhcdn.ru/employer-logo/7201135.png",
            "240": "https://img.hhcdn.ru/employer-logo/7201136.png"
          },
          "vacancies_url": "https://api.hh.ru/vacancies?employer_id=637743",
          "accredited_it_employer": false,
          "trusted": true
        },
        "snippet": {
          "requirement": "Желательно: - Опыт создания интерактивных планов или схем. - Знание fabric.js. - Опыт работы с <highlighttext>Python</highlighttext>, Redis, PostgreSQL. - Опыт настройки Nginx, работы с...",
          "responsibility": "Разработка пользовательского интерфейса сервера для мониторинга и управления бизнес-задачами автоматизированной складской техники. - Взаимодействие с командой проектировщиков и backend-разработчиков..."
        },
        "contacts": null,
        "schedule": {
          "id": "fullDay",
          "name": "Полный день"
        },
        "working_days": [],
        "working_time_intervals": [],
        "working_time_modes": [],
        "accept_temporary": false,
        "fly_in_fly_out_duration": [],
        "work_format": [
          {
            "id": "HYBRID",
            "name": "Гибрид"
          }
        ],
        "working_hours": [
          {
            "id": "HOURS_8",
            "name": "8 часов"
          }
        ],
        "work_schedule_by_days": [
          {
            "id": "FIVE_ON_TWO_OFF",
            "name": "5/2"
          }
        ],
        "night_shifts": false,
        "professional_roles": [
          {
            "id": "96",
            "name": "Программист, разработчик"
          }
        ],
        "accept_incomplete_resumes": false,
        "experience": {
          "id": "between3And6",
          "name": "От 3 до 6 лет"
        },
        "employment": {
          "id": "full",
          "name": "Полная занятость"
        },
        "employment_form": {
          "id": "FULL",
          "name": "Полная"
        },
        "internship": false,
        "adv_response_url": null,
        "is_adv_vacancy": false,
        "adv_context": null
      },
      {
        "id": "124562904",
        "premium": false,
        "name": "Data Scientist в команду Интегрированного бизнес-планирования",
        "department": null,
        "has_test": false,
        "response_letter_required": false,
        "area": {
          "id": "1",
          "name": "Москва",
          "url": "https://api.hh.ru/areas/1"
        },
        "salary": null,
        "salary_range": null,
        "type": {
          "id": "open",
          "name": "Открытая"
        },
        "address": null,
        "response_url": null,
        "sort_point_distance": null,
        "published_at": "2025-08-27T18:41:04+0300",
        "created_at": "2025-08-27T18:41:04+0300",
        "archived": false,
        "apply_alternate_url": "https://hh.ru/applicant/vacancy_response?vacancyId=124562904",
        "branding": {
          "type": "MAKEUP",
          "tariff": null
        },
        "show_logo_in_search": true,
        "show_contacts": true,
        "insider_interview": null,
        "url": "https://api.hh.ru/vacancies/124562904?host=hh.ru",
        "alternate_url": "https://hh.ru/vacancy/124562904",
        "relations": [],
        "employer": {
          "id": "9352463",
          "name": "X5 Tech",
          "url": "https://api.hh.ru/employers/9352463",
          "alternate_url": "https://hh.ru/employer/9352463",
          "logo_urls": {
            "original": "https://img.hhcdn.ru/employer-logo-original/1076836.jpg",
            "90": "https://img.hhcdn.ru/employer-logo/5927973.jpeg",
            "240": "https://img.hhcdn.ru/employer-logo/5927974.jpeg"
          },
          "vacancies_url": "https://api.hh.ru/vacancies?employer_id=9352463",
          "accredited_it_employer": true,
          "trusted": true
        },
        "snippet": {
          "requirement": "Опыт в качестве Data Scientist или ML engineer от 3ех лет. Знание <highlighttext>Python</highlighttext>. Знание классических алгоритмов и структур данных. ",
          "responsibility": "Решать оптимизационные и ML задачи в IBP, связанные с планированием товаропотока, отвечать за техническое развитие продукта, глубоко погружаться в бизнес..."
        },
        "contacts": null,
        "schedule": {
          "id": "remote",
          "name": "Удаленная работа"
        },
        "working_days": [],
        "working_time_intervals": [],
        "working_time_modes": [],
        "accept_temporary": false,
        "fly_in_fly_out_duration": [],
        "work_format": [
          {
            "id": "REMOTE",
            "name": "Удалённо"
          },
          {
            "id": "HYBRID",
            "name": "Гибрид"
          }
        ],
        "working_hours": [
          {
            "id": "HOURS_8",
            "name": "8 часов"
          }
        ],
        "work_schedule_by_days": [
          {
            "id": "FIVE_ON_TWO_OFF",
            "name": "5/2"
          }
        ],
        "night_shifts": false,
        "professional_roles": [
          {
            "id": "165",
            "name": "Дата-сайентист"
          }
        ],
        "accept_incomplete_resumes": false,
        "experience": {
          "id": "between3And6",
          "name": "От 3 до 6 лет"
        },
        "employment": {
          "id": "full",
          "name": "Полная занятость"
        },
        "employment_form": {
          "id": "FULL",
          "name": "Полная"
        },
        "internship": false,
        "adv_response_url": null,
        "is_adv_vacancy": false,
        "adv_context": null
      },
      {
        "id": "120337937",
        "premium": false,
        "name": "Инженер по применению (г. Зеленоград)",
        "department": null,
        "has_test": false,
        "response_letter_required": false,
        "area": {
          "id": "2088",
          "name": "Зеленоград",
          "url": "https://api.hh.ru/areas/2088"
        },
        "salary": null,
        "salary_range": null,
        "type": {
          "id": "open",
          "name": "Открытая"
        },
        "address": {
          "city": "Зеленоград",
          "street": "улица Академика Валиева",
          "building": "6с1",
          "lat": 56.013211,
          "lng": 37.191852,
          "description": null,
          "raw": "Зеленоград, улица Академика Валиева, 6с1",
          "metro": null,
          "metro_stations": [],
          "id": "14104317"
        },
        "response_url": null,
        "sort_point_distance": null,
        "published_at": "2025-08-27T11:29:39+0300",
        "created_at": "2025-08-27T11:29:39+0300",
        "archived": false,
        "apply_alternate_url": "https://hh.ru/applicant/vacancy_response?vacancyId=120337937",
        "branding": {
          "type": "CONSTRUCTOR",
          "tariff": "BASIC"
        },
        "show_logo_in_search": true,
        "show_contacts": false,
        "insider_interview": null,
        "url": "https://api.hh.ru/vacancies/120337937?host=hh.ru",
        "alternate_url": "https://hh.ru/vacancy/120337937",
        "relations": [],
        "employer": {
          "id": "1423697",
          "name": "Группа компаний Микрон",
          "url": "https://api.hh.ru/employers/1423697",
          "alternate_url": "https://hh.ru/employer/1423697",
          "logo_urls": {
            "original": "https://img.hhcdn.ru/employer-logo-original/1398885.png",
            "90": "https://img.hhcdn.ru/employer-logo/7215311.png",
            "240": "https://img.hhcdn.ru/employer-logo/7215312.png"
          },
          "vacancies_url": "https://api.hh.ru/vacancies?employer_id=1423697",
          "accredited_it_employer": false,
          "trusted": true
        },
        "snippet": {
          "requirement": "Понимание основ электроники и схемотехники. Опыт работы со скриптовыми языками TCL, <highlighttext>Python</highlighttext>. Опыт работы с clang: Опыт работы с инструментами...",
          "responsibility": "Обеспечивать техническую поддержку пользователей по работе с микроконтроллерами. Сбор обратной связи и взаимодействие с пользователями. Проведение семинаров, тренингов по работе..."
        },
        "contacts": null,
        "schedule": {
          "id": "fullDay",
          "name": "Полный день"
        },
        "working_days": [],
        "working_time_intervals": [],
        "working_time_modes": [],
        "accept_temporary": false,
        "fly_in_fly_out_duration": [],
        "work_format": [
          {
            "id": "ON_SITE",
            "name": "На месте работодателя"
          },
          {
            "id": "HYBRID",
            "name": "Гибрид"
          }
        ],
        "working_hours": [
          {
            "id": "HOURS_8",
            "name": "8 часов"
          }
        ],
        "work_schedule_by_days": [
          {
            "id": "FIVE_ON_TWO_OFF",
            "name": "5/2"
          }
        ],
        "night_shifts": false,
        "professional_roles": [
          {
            "id": "121",
            "name": "Специалист технической поддержки"
          }
        ],
        "accept_incomplete_resumes": true,
        "experience": {
          "id": "between1And3",
          "name": "От 1 года до 3 лет"
        },
        "employment": {
          "id": "full",
          "name": "Полная занятость"
        },
        "employment_form": {
          "id": "FULL",
          "name": "Полная"
        },
        "internship": false,
        "adv_response_url": null,
        "is_adv_vacancy": false,
        "adv_context": null
      },
      {
        "id": "122300685",
        "premium": false,
        "name": "Руководитель дежурной смены SRE Финтеха",
        "department": {
          "id": "yandex-1740-finplfan",
          "name": "Финтех, Плюс Фантех "
        },
        "has_test": false,
        "response_letter_required": false,
        "area": {
          "id": "1",
          "name": "Москва",
          "url": "https://api.hh.ru/areas/1"
        },
        "salary": null,
        "salary_range": null,
        "type": {
          "id": "open",
          "name": "Открытая"
        },
        "address": {
          "city": "Москва",
          "street": "Садовническая улица",
          "building": "82с2",
          "lat": 55.73552,
          "lng": 37.642474,
          "description": null,
          "raw": "Москва, Садовническая улица, 82с2",
          "metro": {
            "station_name": "Павелецкая",
            "line_name": "Замоскворецкая",
            "station_id": "2.101",
            "line_id": "2",
            "lat": 55.729741,
            "lng": 37.638693
          },
          "metro_stations": [
            {
              "station_name": "Павелецкая",
              "line_name": "Замоскворецкая",
              "station_id": "2.101",
              "line_id": "2",
              "lat": 55.729741,
              "lng": 37.638693
            },
            {
              "station_name": "Павелецкая",
              "line_name": "Кольцевая",
              "station_id": "5.102",
              "line_id": "5",
              "lat": 55.731414,
              "lng": 37.636294
            }
          ],
          "id": "840360"
        },
        "response_url": null,
        "sort_point_distance": null,
        "published_at": "2025-08-27T10:48:01+0300",
        "created_at": "2025-08-27T10:48:01+0300",
        "archived": false,
        "apply_alternate_url": "https://hh.ru/applicant/vacancy_response?vacancyId=122300685",
        "show_logo_in_search": null,
        "show_contacts": false,
        "insider_interview": null,
        "url": "https://api.hh.ru/vacancies/122300685?host=hh.ru",
        "alternate_url": "https://hh.ru/vacancy/122300685",
        "relations": [],
        "employer": {
          "id": "1740",
          "name": "Яндекс",
          "url": "https://api.hh.ru/employers/1740",
          "alternate_url": "https://hh.ru/employer/1740",
          "logo_urls": {
            "original": "https://img.hhcdn.ru/employer-logo-original/837491.png",
            "90": "https://img.hhcdn.ru/employer-logo/3790847.png",
            "240": "https://img.hhcdn.ru/employer-logo/3790848.png"
          },
          "vacancies_url": "https://api.hh.ru/vacancies?employer_id=1740",
          "accredited_it_employer": false,
          "trusted": true
        },
        "snippet": {
          "requirement": "Стрессоустойчивы, самостоятельны в кризисных сценариях. Работали с Ansible, Puppet или другими инструментами автоматизации. Писали код на <highlighttext>Python</highlighttext> или Go.",
          "responsibility": "Управление дежурной сменой. Вы организуете работу команды и будете контролировать качество и эффективность. Важно улучшать процессы взаимодействия внутри команды и..."
        },
        "contacts": null,
        "schedule": {
          "id": "fullDay",
          "name": "Полный день"
        },
        "working_days": [],
        "working_time_intervals": [],
        "working_time_modes": [],
        "accept_temporary": false,
        "fly_in_fly_out_duration": [],
        "work_format": [
          {
            "id": "HYBRID",
            "name": "Гибрид"
          }
        ],
        "working_hours": [
          {
            "id": "HOURS_8",
            "name": "8 часов"
          }
        ],
        "work_schedule_by_days": [
          {
            "id": "FIVE_ON_TWO_OFF",
            "name": "5/2"
          }
        ],
        "night_shifts": false,
        "professional_roles": [
          {
            "id": "82",
            "name": "Начальник смены, мастер участка"
          }
        ],
        "accept_incomplete_resumes": false,
        "experience": {
          "id": "moreThan6",
          "name": "Более 6 лет"
        },
        "employment": {
          "id": "full",
          "name": "Полная занятость"
        },
        "employment_form": {
          "id": "FULL",
          "name": "Полная"
        },
        "internship": false,
        "adv_response_url": null,
        "is_adv_vacancy": false,
        "adv_context": null
      }
    ],
    "found": 505,
    "pages": 11,
    "page": 10,
    "per_page": 50,
    "clusters": null,
    "arguments": null,
    "fixes": null,
    "suggests": null,
    "alternate_url": "https://hh.ru/search/vacancy?area=1&enable_snippets=true&items_on_page=50&page=10&search_period=1&text=python"
  }
}