{
  "timestamp": 1757171013.1907253,
  "meta": {
    "params": {
      "area": 113,
      "per_page": 50,
      "only_with_salary": false,
      "period": 15,
      "text": "python developer",
      "page": 8
    }
  },
  "data": {
    "items": [],
    "found": 3973,
    "pages": 40,
    "page": 8,
    "per_page": 50,
    "clusters": null,
    "arguments": null,
    "fixes": null,
    "suggests": null,
    "alternate_url": "https://hh.ru/search/vacancy?area=113&enable_snippets=true&items_on_page=50&page=8&search_period=15&text=python+developer"
  }
}